easy_mq/__init__.py
easy_mq/base.py
easy_mq/queue.py
easy_mq/test_queue.py
easy_mq/tools.py
easy_mq-0.1.2.dist-info/METADATA
easy_mq-0.1.2.dist-info/RECORD
easy_mq-0.1.2.dist-info/WHEEL
easy_mq-0.1.2.dist-info/top_level.txt
