Metadata-Version: 2.1
Name: easy-mq
Version: 0.1.2
Summary: Library for using RabbitMQ with python (async/sync).
Home-page: https://github.com/recrut-as/easy_mq
Author: Halvor Bø
Author-email: halvor@recrut.no
License: UNKNOWN
Platform: UNKNOWN
Classifier: Programming Language :: Python :: 3
Classifier: License :: OSI Approved :: MIT License
Classifier: Operating System :: OS Independent
Requires-Dist: pika
Requires-Dist: aio-pika
